confmap/__init__.py
confmap/functions.py
confmap/hyperbolic.py
confmap/imagetrans.py
confmap/mapping.py
confmap/mask.py
confmap/version.py
confmap/videotrans.py
confmap-1.0.9.dist-info/DESCRIPTION.rst
confmap-1.0.9.dist-info/METADATA
confmap-1.0.9.dist-info/RECORD
confmap-1.0.9.dist-info/WHEEL
confmap-1.0.9.dist-info/metadata.json
confmap-1.0.9.dist-info/top_level.txt
tests/__init__.py
tests/test_tilesAndTransform.py
tests/test_tilesAndTransforms.py
tests/test_tiling.py
tests/test_transform.py
