Metadata-Version: 2.0
Name: confmap
Version: 1.0.9
Summary: Conformal mapping on images and videos
Home-page: https://github.com/FCoulombeau/confmap
Author: F.Coulombeau 2019
Author-email: coulombeau@gmail.com
License: MIT License
Keywords: conformal mapping complex analysis
Platform: UNKNOWN
Classifier: Development Status :: 5 - Production/Stable
Classifier: Intended Audience :: Developers
Classifier: Natural Language :: English
Classifier: Natural Language :: French
Classifier: License :: OSI Approved :: MIT License
Classifier: Programming Language :: Python
Classifier: Programming Language :: Python :: 3
Classifier: Programming Language :: Python :: 3.4
Classifier: Programming Language :: Python :: 3.5
Classifier: Programming Language :: Python :: 3.6
Classifier: Topic :: Multimedia
Classifier: Topic :: Multimedia :: Video
Provides-Extra: doc
Provides-Extra: test
Provides-Extra: optional
Requires-Dist: numpy
Requires-Dist: moviepy
Requires-Dist: matplotlib (<3.0,>=2.0.0); python_version >= "3.4"
Provides-Extra: doc
Requires-Dist: numpydoc (<1.0,>=0.6.0); extra == 'doc'
Requires-Dist: sphinx-rtd-theme (<1.0,>=0.1.10b0); extra == 'doc'
Requires-Dist: Sphinx (<2.0,>=1.5.2); extra == 'doc'
Provides-Extra: optional
Provides-Extra: test
Requires-Dist: pytest (<4.4,>=3.0.0); extra == 'test'
